TujieMingxiang/Dockerfile
TujieMingxiang/README.md
TujieMingxiang/__init__.py
TujieMingxiang/__main__.py
TujieMingxiang/file.epub
TujieMingxiang/index.html
TujieMingxiang/css/__init__.py
TujieMingxiang/css/annotations.css
TujieMingxiang/css/main.css
TujieMingxiang/css/normalize.css
TujieMingxiang/css/popup.css
TujieMingxiang/font/__init__.py
TujieMingxiang/font/fontello.eot
TujieMingxiang/font/fontello.svg
TujieMingxiang/font/fontello.ttf
TujieMingxiang/font/fontello.woff
TujieMingxiang/img/__init__.py
TujieMingxiang/img/annotator-glyph-sprite.png
TujieMingxiang/img/annotator-icon-sprite.png
TujieMingxiang/img/apple-touch-icon.png
TujieMingxiang/img/cancelfullscreen.png
TujieMingxiang/img/close.png
TujieMingxiang/img/fullscreen.png
TujieMingxiang/img/loader.gif
TujieMingxiang/img/menu-icon.png
TujieMingxiang/img/save.png
TujieMingxiang/img/saved.png
TujieMingxiang/img/settings-s.png
TujieMingxiang/img/settings.png
TujieMingxiang/img/star.png
TujieMingxiang/js/__init__.py
TujieMingxiang/js/epub.js
TujieMingxiang/js/epub.min.js
TujieMingxiang/js/epub.min.map
TujieMingxiang/js/hooks.min.js
TujieMingxiang/js/hooks.min.map
TujieMingxiang/js/reader.js
TujieMingxiang/js/reader.js.map
TujieMingxiang/js/reader.min.js
TujieMingxiang/js/reader.min.map
TujieMingxiang/js/hooks/__init__.py
TujieMingxiang/js/hooks/extensions/__init__.py
TujieMingxiang/js/hooks/extensions/highlight.js
TujieMingxiang/js/libs/__init__.py
TujieMingxiang/js/libs/jquery.min.js
TujieMingxiang/js/libs/localforage.min.js
TujieMingxiang/js/libs/screenfull.js
TujieMingxiang/js/libs/screenfull.min.js
TujieMingxiang/js/libs/zip.min.js
TujieMingxiang/js/plugins/__init__.py
TujieMingxiang/js/plugins/hypothesis.js
TujieMingxiang/js/plugins/search.js
tujie_mingxiang-2022.10.9.1.dist-info/METADATA
tujie_mingxiang-2022.10.9.1.dist-info/WHEEL
tujie_mingxiang-2022.10.9.1.dist-info/entry_points.txt
tujie_mingxiang-2022.10.9.1.dist-info/top_level.txt
tujie_mingxiang-2022.10.9.1.dist-info/RECORD
